{
  "id": 2,
  "username": "Emily",
  "username_canonical": "emily",
  "enabled": false,
  "channels": [
    {
      "id": 1,
      "name": "sfdg",
      "slug": "dafg",
      "irc_channel": "#sfdg",
      "count_visits": 0,
      "number_fans": 0,
      "channel_type": {
        "name": "locale"
      },
      "publicated_at": "2014-02-25 09:26:20"
    },
    {
      "id": 2,
      "name": "Canada",
      "slug": "canada",
      "irc_channel": "#canada",
      "description": "Free chat room of people in country Canada",
      "count_visits": 0,
      "number_fans": 0,
      "channel_type": {
        "name": "locale"
      },
      "publicated_at": "2014-02-25 09:26:20"
    }
  ],
  "channels_fan": [
    {
      "id": 100,
      "name": "Columbia",
      "slug": "columbia",
      "irc_channel": "#columbia",
      "description": "Join free Columbia Chat Rooms of United States",
      "count_visits": 0,
      "number_fans": 1,
      "channel_type": {
        "name": "locale"
      },
      "publicated_at": "2014-02-25 09:26:29"
    }
  ],
  "channels_moderated": [
    {
      "id": 1,
      "name": "sfdg",
      "slug": "dafg",
      "irc_channel": "#sfdg",
      "count_visits": 0,
      "number_fans": 0,
      "channel_type": {
        "name": "locale"
      },
      "publicated_at": "2014-02-25 09:26:20"
    },
    {
      "id": 2,
      "name": "Canada",
      "slug": "canada",
      "irc_channel": "#canada",
      "description": "Free chat room of people in country Canada",
      "count_visits": 0,
      "number_fans": 0,
      "channel_type": {
        "name": "locale"
      },
      "publicated_at": "2014-02-25 09:26:20"
    }

  ],
  "profile": {
    "seeking": "women",
    "gender": "female",
    "birthday": "1993-10-30T00:00:00+0100",
    "count_visits": 0,
    "profile_photo": {
      "id": 628,
      "publicated_at": "2014-02-25T09:25:57+0100",
      "number_votes": 0,
      "score": 0,
      "path": "http://api.chateagratis.local/uploads/original/2014/02/25/530c53953d217.jpg",
      "path_large": "http://api.chateagratis.local/uploads/original/2014/02/25/530c53953d217_large.jpg",
      "path_medium": "http://api.chateagratis.local/uploads/original/2014/02/25/530c53953d217_medium.jpg",
      "path_small": "http://api.chateagratis.local/uploads/original/2014/02/25/530c53953d217_small.jpg",
      "path_icon": "http://api.chateagratis.local/uploads/original/2014/02/25/530c53953d217_icon.jpg"
    }
  },
  "city": {
    "name": "Rothville",
    "id": 121218
  },
  "client": {
    "id": 13,
    "name": "chateagratis-web",
    "affiliate": {
      "id": 1,
      "name": "ant web"
    }
  },
  "_links": {
    "self": {
      "href": "http://api.chateagratis.local/app_dev.php/api/users/2"
    },
    "channels": {
      "href": "http://api.chateagratis.local/app_dev.php/api/users/2/channels"
    },
    "channels_fan": {
      "href": "http://api.chateagratis.local/app_dev.php/api/users/2/channelsFan"
    },
    "blocked_users": {
      "href": "http://api.chateagratis.local/app_dev.php/api/users/2/blocked"
    },
    "photos": {
      "href": "http://api.chateagratis.local/app_dev.php/api/users/2/photos"
    },
    "channels_moderated": {
      "href": "http://api.chateagratis.local/app_dev.php/api/users/2/moderated"
    }
  }
}